Metadata-Version: 1.0
Name: queueManager
Version: 0.1.1
Summary: distribute multi-process
Home-page: http://gdwrobot.cn/
Author: wangzongzheng
Author-email: wangzongzheng@126.com
License: MIT
Keywords: distribute multi-process
Platform: UNKNOWN
